parus/__init__.py
parus/__main__.py
parus/auth.py
parus/config.py
parus/download.py
parus/google.py
parus/main.py
parus/search.py
parus/update.py
parus/upload.py
parus/util.py
test/__init__.py
test/config_fixture.py
test/conftest.py
test/drive_service_fixture.py
test/test_auth.py
test/test_config.py
test/test_download.py
test/test_main.py
test/test_search.py
test/test_update.py
test/test_upload.py
parus-0.2.0.dist-info/LICENSE
parus-0.2.0.dist-info/METADATA
parus-0.2.0.dist-info/WHEEL
parus-0.2.0.dist-info/entry_points.txt
parus-0.2.0.dist-info/top_level.txt
parus-0.2.0.dist-info/RECORD
