Metadata-Version: 2.1
Name: parus
Version: 0.2.0
Summary: Google Drive CLI tool
Home-page: https://github.com/kikuchi-m/parus
Author: Kikuchi Motoki
Author-email: wildflower.pink0102@gmail.com
License: MIT
Platform: UNKNOWN
Classifier: Development Status :: 3 - Alpha
Classifier: Environment :: Console
Classifier: Intended Audience :: Developers
Requires-Python: >=3.7.5
Requires-Dist: google-api-python-client (>=2.58.0)
Requires-Dist: google-auth-httplib2 (>=0.1.0)
Requires-Dist: google-auth-oauthlib (>=0.5.2)
